github_bot/__init__.py
github_bot/__main__.py
github_bot/util.py
github_bot/wip.py
github_bot-0.0.1.dist-info/LICENSE
github_bot-0.0.1.dist-info/WHEEL
github_bot-0.0.1.dist-info/METADATA
github_bot-0.0.1.dist-info/RECORD
